Workbook

Sheet Main
A1: Index | B1: Date | C1: Category | D1: Sub Category | E1: =CONCATENATE("Amount (", -SUM(E2:E1032) ,")") -> Amount (39050.57) | F1: =CONCATENATE("Balance (", F2+SUM(E2:E1032) ,")") -> Balance (62226.34) | G1: Notes | H1: Groups | I1: Month | J1: Year | K1: Year-Month
A2: 1 | B2: 45505 | E2: 0 | F2: =101276.91 -> 101276.91 | I2: =IF(ISBLANK(A2), "", MONTH(B2)) -> 8 | J2: =IF(ISBLANK(A2), "", YEAR(B2)) -> 2024 | K2: =IF(ISBLANK(A2), "", CONCATENATE(J2," - ",I2)) -> 2024 - 8
A3: 2 | B3: 45505 | C3: Misc | D3: Personal | E3: =-300 -> -300 | F3: =IF(ISBLANK(A3),"", F2+E3) -> 100976.91 | G3: License | I3: =IF(ISBLANK(A3), "", MONTH(B3)) -> 8 | J3: =IF(ISBLANK(A3), "", YEAR(B3)) -> 2024 | K3: =IF(ISBLANK(A3), "", CONCATENATE(J3," - ",I3)) -> 2024 - 8
A4: 3 | B4: 45505 | C4: Lend | D4: Others | E4: =-1500 -> -1500 | F4: =IF(ISBLANK(A4),"", F3+E4) -> 99476.91 | G4: Snehith | H4: G6 | I4: =IF(ISBLANK(A4), "", MONTH(B4)) -> 8 | J4: =IF(ISBLANK(A4), "", YEAR(B4)) -> 2024 | K4: =IF(ISBLANK(A4), "", CONCATENATE(J4," - ",I4)) -> 2024 - 8
A5: 4 | B5: 45505 | C5: Shop | D5: Personal | E5: =-531 -> -531 | F5: =IF(ISBLANK(A5),"", F4+E5) -> 98945.91 | G5: Convocation Shirt | I5: =IF(ISBLANK(A5), "", MONTH(B5)) -> 8 | J5: =IF(ISBLANK(A5), "", YEAR(B5)) -> 2024 | K5: =IF(ISBLANK(A5), "", CONCATENATE(J5," - ",I5)) -> 2024 - 8
A6: 5 | B6: 45505 | C6: Shop | D6: Personal | E6: =-500 -> -500 | F6: =IF(ISBLANK(A6),"", F5+E6) -> 98445.91 | G6: Convocation Shirt | I6: =IF(ISBLANK(A6), "", MONTH(B6)) -> 8 | J6: =IF(ISBLANK(A6), "", YEAR(B6)) -> 2024 | K6: =IF(ISBLANK(A6), "", CONCATENATE(J6," - ",I6)) -> 2024 - 8
A7: 6 | B7: 45505 | C7: Food | D7: Personal | E7: =-551 -> -551 | F7: =IF(ISBLANK(A7),"", F6+E7) -> 97894.91 | G7: Truffles Order | I7: =IF(ISBLANK(A7), "", MONTH(B7)) -> 8 | J7: =IF(ISBLANK(A7), "", YEAR(B7)) -> 2024 | K7: =IF(ISBLANK(A7), "", CONCATENATE(J7," - ",I7)) -> 2024 - 8
A8: 7 | B8: 45506 | C8: Misc | D8: Family | E8: =-200 -> -200 | F8: =IF(ISBLANK(A8),"", F7+E8) -> 97694.91 | G8: Mom's Kitty | I8: =IF(ISBLANK(A8), "", MONTH(B8)) -> 8 | J8: =IF(ISBLANK(A8), "", YEAR(B8)) -> 2024 | K8: =IF(ISBLANK(A8), "", CONCATENATE(J8," - ",I8)) -> 2024 - 8
A9: 8 | B9: 45510 | C9: Fuel | D9: Personal | E9: -393.91 | F9: =IF(ISBLANK(A9),"", F8+E9) -> 97301 | G9: Scooty | I9: =IF(ISBLANK(A9), "", MONTH(B9)) -> 8 | J9: =IF(ISBLANK(A9), "", YEAR(B9)) -> 2024 | K9: =IF(ISBLANK(A9), "", CONCATENATE(J9," - ",I9)) -> 2024 - 8
A10: 9 | B10: 45510 | C10: Split Return | D10: Others | E10: 8692 | F10: =IF(ISBLANK(A10),"", F9+E10) -> 105993 | G10: Bhavye Ticket | I10: =IF(ISBLANK(A10), "", MONTH(B10)) -> 8 | J10: =IF(ISBLANK(A10), "", YEAR(B10)) -> 2024 | K10: =IF(ISBLANK(A10), "", CONCATENATE(J10," - ",I10)) -> 2024 - 8
A11: 10 | B11: 45511 | C11: Food | D11: Family | E11: -245 | F11: =IF(ISBLANK(A11),"", F10+E11) -> 105748 | G11: Chat | I11: =IF(ISBLANK(A11), "", MONTH(B11)) -> 8 | J11: =IF(ISBLANK(A11), "", YEAR(B11)) -> 2024 | K11: =IF(ISBLANK(A11), "", CONCATENATE(J11," - ",I11)) -> 2024 - 8
A12: 11 | B12: 45512 | C12: Shop | D12: Family | E12: -4999 | F12: =IF(ISBLANK(A12),"", F11+E12) -> 100749 | G12: Muskan | I12: =IF(ISBLANK(A12), "", MONTH(B12)) -> 8 | J12: =IF(ISBLANK(A12), "", YEAR(B12)) -> 2024 | K12: =IF(ISBLANK(A12), "", CONCATENATE(J12," - ",I12)) -> 2024 - 8
A13: 12 | B13: 45512 | C13: Shop | D13: Family | E13: -5998 | F13: =IF(ISBLANK(A13),"", F12+E13) -> 94751 | G13: Muskan | I13: =IF(ISBLANK(A13), "", MONTH(B13)) -> 8 | J13: =IF(ISBLANK(A13), "", YEAR(B13)) -> 2024 | K13: =IF(ISBLANK(A13), "", CONCATENATE(J13," - ",I13)) -> 2024 - 8
A14: 13 | B14: 45513 | C14: Shop | D14: Personal | E14: -2490 | F14: =IF(ISBLANK(A14),"", F13+E14) -> 92261 | G14: Pant Project | I14: =IF(ISBLANK(A14), "", MONTH(B14)) -> 8 | J14: =IF(ISBLANK(A14), "", YEAR(B14)) -> 2024 | K14: =IF(ISBLANK(A14), "", CONCATENATE(J14," - ",I14)) -> 2024 - 8
A15: 14 | B15: 45513 | C15: Shop | D15: Others | E15: -1416 | F15: =IF(ISBLANK(A15),"", F14+E15) -> 90845 | G15: Shreyas Gift | I15: =IF(ISBLANK(A15), "", MONTH(B15)) -> 8 | J15: =IF(ISBLANK(A15), "", YEAR(B15)) -> 2024 | K15: =IF(ISBLANK(A15), "", CONCATENATE(J15," - ",I15)) -> 2024 - 8
A16: 15 | B16: 45514 | C16: Split Return | D16: Others | E16: 300 | F16: =IF(ISBLANK(A16),"", F15+E16) -> 91145 | G16: Imtiyaz, Shreyas Gift | I16: =IF(ISBLANK(A16), "", MONTH(B16)) -> 8 | J16: =IF(ISBLANK(A16), "", YEAR(B16)) -> 2024 | K16: =IF(ISBLANK(A16), "", CONCATENATE(J16," - ",I16)) -> 2024 - 8
A17: 16 | B17: 45514 | C17: Travel | D17: Personal | E17: -131 | F17: =IF(ISBLANK(A17),"", F16+E17) -> 91014 | G17: Auto | I17: =IF(ISBLANK(A17), "", MONTH(B17)) -> 8 | J17: =IF(ISBLANK(A17), "", YEAR(B17)) -> 2024 | K17: =IF(ISBLANK(A17), "", CONCATENATE(J17," - ",I17)) -> 2024 - 8
A18: 17 | B18: 45514 | C18: Shop | D18: Others | E18: -3117 | F18: =IF(ISBLANK(A18),"", F17+E18) -> 87897 | G18: TEDx Photos | I18: =IF(ISBLANK(A18), "", MONTH(B18)) -> 8 | J18: =IF(ISBLANK(A18), "", YEAR(B18)) -> 2024 | K18: =IF(ISBLANK(A18), "", CONCATENATE(J18," - ",I18)) -> 2024 - 8
A19: 18 | B19: 45514 | C19: Travel | D19: Personal | E19: -190 | F19: =IF(ISBLANK(A19),"", F18+E19) -> 87707 | G19: Auto | I19: =IF(ISBLANK(A19), "", MONTH(B19)) -> 8 | J19: =IF(ISBLANK(A19), "", YEAR(B19)) -> 2024 | K19: =IF(ISBLANK(A19), "", CONCATENATE(J19," - ",I19)) -> 2024 - 8
A20: 19 | B20: 45514 | C20: Food | D20: Personal | E20: -98 | F20: =IF(ISBLANK(A20),"", F19+E20) -> 87609 | G20: Lunch | I20: =IF(ISBLANK(A20), "", MONTH(B20)) -> 8 | J20: =IF(ISBLANK(A20), "", YEAR(B20)) -> 2024 | K20: =IF(ISBLANK(A20), "", CONCATENATE(J20," - ",I20)) -> 2024 - 8
... A26: 25 | B26: 45515 | C26: Shop | D26: Family | E26: -3422 | F26: =IF(ISBLANK(A26),"", F25+E26) -> 53454 | G26: Mandala Frame | I26: =IF(ISBLANK(A26), "", MONTH(B26)) -> 8 | J26: =IF(ISBLANK(A26), "", YEAR(B26)) -> 2024 | K26: =IF(ISBLANK(A26), "", CONCATENATE(J26," - ",I26)) -> 2024 - 8
A27: 26 | B27: 45515 | C27: Fun | D27: Personal, Others | E27: -7996 | F27: =IF(ISBLANK(A27),"", F26+E27) -> 45458 | G27: Kanva Camp | H27: G1 | I27: =IF(ISBLANK(A27), "", MONTH(B27)) -> 8 | J27: =IF(ISBLANK(A27), "", YEAR(B27)) -> 2024 | K27: =IF(ISBLANK(A27), "", CONCATENATE(J27," - ",I27)) -> 2024 - 8
A28: 27 | B28: 45515 | C28: Travel | D28: Personal | E28: -456 | F28: =IF(ISBLANK(A28),"", F27+E28) -> 45002 | G28: Auto | I28: =IF(ISBLANK(A28), "", MONTH(B28)) -> 8 | J28: =IF(ISBLANK(A28), "", YEAR(B28)) -> 2024 | K28: =IF(ISBLANK(A28), "", CONCATENATE(J28," - ",I28)) -> 2024 - 8
A29: 28 | B29: 45516 | C29: Shop | D29: Personal | E29: -1449 | F29: =IF(ISBLANK(A29),"", F28+E29) -> 43553 | G29: Power bank | I29: =IF(ISBLANK(A29), "", MONTH(B29)) -> 8 | J29: =IF(ISBLANK(A29), "", YEAR(B29)) -> 2024 | K29: =IF(ISBLANK(A29), "", CONCATENATE(J29," - ",I29)) -> 2024 - 8
A30: 29 | B30: 45516 | C30: Transfer | D30: Family | E30: -15000 | F30: =IF(ISBLANK(A30),"", F29+E30) -> 28553 | G30: Muskaan | I30: =IF(ISBLANK(A30), "", MONTH(B30)) -> 8 | J30: =IF(ISBLANK(A30), "", YEAR(B30)) -> 2024 | K30: =IF(ISBLANK(A30), "", CONCATENATE(J30," - ",I30)) -> 2024 - 8
A31: 30 | B31: 45518 | C31: Travel | D31: Personal | E31: -192 | F31: =IF(ISBLANK(A31),"", F30+E31) -> 28361 | G31: Auto | I31: =IF(ISBLANK(A31), "", MONTH(B31)) -> 8 | J31: =IF(ISBLANK(A31), "", YEAR(B31)) -> 2024 | K31: =IF(ISBLANK(A31), "", CONCATENATE(J31," - ",I31)) -> 2024 - 8
A32: 31 | B32: 45518 | C32: Travel | D32: Personal | E32: -42.75 | F32: =IF(ISBLANK(A32),"", F31+E32) -> 28318.25 | G32: Metro | I32: =IF(ISBLANK(A32), "", MONTH(B32)) -> 8 | J32: =IF(ISBLANK(A32), "", YEAR(B32)) -> 2024 | K32: =IF(ISBLANK(A32), "", CONCATENATE(J32," - ",I32)) -> 2024 - 8
A33: 32 | B33: 45518 | C33: Travel | D33: Personal | E33: -128 | F33: =IF(ISBLANK(A33),"", F32+E33) -> 28190.25 | G33: Auto | I33: =IF(ISBLANK(A33), "", MONTH(B33)) -> 8 | J33: =IF(ISBLANK(A33), "", YEAR(B33)) -> 2024 | K33: =IF(ISBLANK(A33), "", CONCATENATE(J33," - ",I33)) -> 2024 - 8
A34: 33 | B34: 45518 | C34: Travel | D34: Personal | E34: -17.1 | F34: =IF(ISBLANK(A34),"", F33+E34) -> 28173.15 | G34: Metro | I34: =IF(ISBLANK(A34), "", MONTH(B34)) -> 8 | J34: =IF(ISBLANK(A34), "", YEAR(B34)) -> 2024 | K34: =IF(ISBLANK(A34), "", CONCATENATE(J34," - ",I34)) -> 2024 - 8
A35: 34 | B35: 45518 | C35: Travel | D35: Personal | E35: -160 | F35: =IF(ISBLANK(A35),"", F34+E35) -> 28013.15 | G35: Auto | I35: =IF(ISBLANK(A35), "", MONTH(B35)) -> 8 | J35: =IF(ISBLANK(A35), "", YEAR(B35)) -> 2024 | K35: =IF(ISBLANK(A35), "", CONCATENATE(J35," - ",I35)) -> 2024 - 8
A36: 35 | B36: 45518 | C36: Food | D36: Personal, Others | E36: -995 | F36: =IF(ISBLANK(A36),"", F35+E36) -> 27018.15 | G36: Bhavye Lebanese | H36: G2 | I36: =IF(ISBLANK(A36), "", MONTH(B36)) -> 8 | J36: =IF(ISBLANK(A36), "", YEAR(B36)) -> 2024 | K36: =IF(ISBLANK(A36), "", CONCATENATE(J36," - ",I36)) -> 2024 - 8
A37: 36 | B37: 45518 | C37: Food | D37: Others | E37: -93 | F37: =IF(ISBLANK(A37),"", F36+E37) -> 26925.15 | G37: Bhavye Mirinda | H37: G2 | I37: =IF(ISBLANK(A37), "", MONTH(B37)) -> 8 | J37: =IF(ISBLANK(A37), "", YEAR(B37)) -> 2024 | K37: =IF(ISBLANK(A37), "", CONCATENATE(J37," - ",I37)) -> 2024 - 8
A38: 37 | B38: 45518 | C38: Travel | D38: Personal | E38: -47.5 | F38: =IF(ISBLANK(A38),"", F37+E38) -> 26877.65 | G38: Metro | I38: =IF(ISBLANK(A38), "", MONTH(B38)) -> 8 | J38: =IF(ISBLANK(A38), "", YEAR(B38)) -> 2024 | K38: =IF(ISBLANK(A38), "", CONCATENATE(J38," - ",I38)) -> 2024 - 8
A39: 38 | B39: 45518 | C39: Travel | D39: Personal | E39: -79.8 | F39: =IF(ISBLANK(A39),"", F38+E39) -> 26797.85 | G39: Metro | H39: G2 | I39: =IF(ISBLANK(A39), "", MONTH(B39)) -> 8 | J39: =IF(ISBLANK(A39), "", YEAR(B39)) -> 2024 | K39: =IF(ISBLANK(A39), "", CONCATENATE(J39," - ",I39)) -> 2024 - 8
A40: 39 | B40: 45518 | C40: Travel | D40: Personal | E40: -122 | F40: =IF(ISBLANK(A40),"", F39+E40) -> 26675.85 | G40: Auto | H40: G2 | I40: =IF(ISBLANK(A40), "", MONTH(B40)) -> 8 | J40: =IF(ISBLANK(A40), "", YEAR(B40)) -> 2024 | K40: =IF(ISBLANK(A40), "", CONCATENATE(J40," - ",I40)) -> 2024 - 8
A41: 40 | B41: 45518 | C41: Shop | D41: Personal | E41: -445 | F41: =IF(ISBLANK(A41),"", F40+E41) -> 26230.85 | G41: Trip Snacks | H41: G1 | I41: =IF(ISBLANK(A41), "", MONTH(B41)) -> 8 | J41: =IF(ISBLANK(A41), "", YEAR(B41)) -> 2024 | K41: =IF(ISBLANK(A41), "", CONCATENATE(J41," - ",I41)) -> 2024 - 8
A42: 41 | B42: 45518 | C42: Monthly Bill | D42: Personal | E42: -649 | F42: =IF(ISBLANK(A42),"", F41+E42) -> 25581.85 | G42: Netflix | H42: G5 | I42: =IF(ISBLANK(A42), "", MONTH(B42)) -> 8 | J42: =IF(ISBLANK(A42), "", YEAR(B42)) -> 2024 | K42: =IF(ISBLANK(A42), "", CONCATENATE(J42," - ",I42)) -> 2024 - 8
A43: 42 | B43: 45520 | C43: Food | D43: Personal, Others | E43: -6777 | F43: =IF(ISBLANK(A43),"", F42+E43) -> 18804.85 | G43: Oia After Kanva | H43: G7 | I43: =IF(ISBLANK(A43), "", MONTH(B43)) -> 8 | J43: =IF(ISBLANK(A43), "", YEAR(B43)) -> 2024 | K43: =IF(ISBLANK(A43), "", CONCATENATE(J43," - ",I43)) -> 2024 - 8
A44: 43 | B44: 45520 | C44: Misc | D44: Personal, Others | E44: -75 | F44: =IF(ISBLANK(A44),"", F43+E44) -> 18729.85 | G44: Eatables | I44: =IF(ISBLANK(A44), "", MONTH(B44)) -> 8 | J44: =IF(ISBLANK(A44), "", YEAR(B44)) -> 2024 | K44: =IF(ISBLANK(A44), "", CONCATENATE(J44," - ",I44)) -> 2024 - 8
A45: 44 | B45: 45520 | C45: Misc | D45: Personal | E45: -100 | F45: =IF(ISBLANK(A45),"", F44+E45) -> 18629.85 | G45: Haircut | I45: =IF(ISBLANK(A45), "", MONTH(B45)) -> 8 | J45: =IF(ISBLANK(A45), "", YEAR(B45)) -> 2024 | K45: =IF(ISBLANK(A45), "", CONCATENATE(J45," - ",I45)) -> 2024 - 8
A46: 45 | B46: 45520 | C46: Shop | D46: Personal | E46: -136 | F46: =IF(ISBLANK(A46),"", F45+E46) -> 18493.85 | G46: hairspray | I46: =IF(ISBLANK(A46), "", MONTH(B46)) -> 8 | J46: =IF(ISBLANK(A46), "", YEAR(B46)) -> 2024 | K46: =IF(ISBLANK(A46), "", CONCATENATE(J46," - ",I46)) -> 2024 - 8
A47: 46 | B47: 45521 | C47: Food | D47: Personal, Others | E47: -7823 | F47: =IF(ISBLANK(A47),"", F46+E47) -> 10670.85 | G47: Maize & Malt | H47: G3 | I47: =IF(ISBLANK(A47), "", MONTH(B47)) -> 8 | J47: =IF(ISBLANK(A47), "", YEAR(B47)) -> 2024 | K47: =IF(ISBLANK(A47), "", CONCATENATE(J47," - ",I47)) -> 2024 - 8
A48: 47 | B48: 45521 | C48: Food | D48: Others | E48: -1045 | F48: =IF(ISBLANK(A48),"", F47+E48) -> 9625.85 | G48: Maize & Malt | H48: G3 | I48: =IF(ISBLANK(A48), "", MONTH(B48)) -> 8 | J48: =IF(ISBLANK(A48), "", YEAR(B48)) -> 2024 | K48: =IF(ISBLANK(A48), "", CONCATENATE(J48," - ",I48)) -> 2024 - 8
A49: 48 | B49: 45521 | C49: Split Return | D49: Others | E49: 430 | F49: =IF(ISBLANK(A49),"", F48+E49) -> 10055.85 | G49: Vishnu | H49: G3 | I49: =IF(ISBLANK(A49), "", MONTH(B49)) -> 8 | J49: =IF(ISBLANK(A49), "", YEAR(B49)) -> 2024 | K49: =IF(ISBLANK(A49), "", CONCATENATE(J49," - ",I49)) -> 2024 - 8
A50: 49 | B50: 45521 | C50: Split Return | D50: Others | E50: 428 | F50: =IF(ISBLANK(A50),"", F49+E50) -> 10483.85 | G50: Mohit | H50: G3 | I50: =IF(ISBLANK(A50), "", MONTH(B50)) -> 8 | J50: =IF(ISBLANK(A50), "", YEAR(B50)) -> 2024 | K50: =IF(ISBLANK(A50), "", CONCATENATE(J50," - ",I50)) -> 2024 - 8
A51: 50 | B51: 45522 | C51: Split Return | D51: Others | E51: 325 | F51: =IF(ISBLANK(A51),"", F50+E51) -> 10808.85 | G51: Snehith | H51: G3 | I51: =IF(ISBLANK(A51), "", MONTH(B51)) -> 8 | J51: =IF(ISBLANK(A51), "", YEAR(B51)) -> 2024 | K51: =IF(ISBLANK(A51), "", CONCATENATE(J51," - ",I51)) -> 2024 - 8
A52: 51 | B52: 45522 | C52: Split Return | D52: Others | E52: 428 | F52: =IF(ISBLANK(A52),"", F51+E52) -> 11236.85 | G52: Imtiyaz | H52: G3 | I52: =IF(ISBLANK(A52), "", MONTH(B52)) -> 8 | J52: =IF(ISBLANK(A52), "", YEAR(B52)) -> 2024 | K52: =IF(ISBLANK(A52), "", CONCATENATE(J52," - ",I52)) -> 2024 - 8
A53: 52 | B53: 45522 | C53: Split Return | D53: Others | E53: 18 | F53: =IF(ISBLANK(A53),"", F52+E53) -> 11254.85 | G53: Imtiyaz | H53: G3 | I53: =IF(ISBLANK(A53), "", MONTH(B53)) -> 8 | J53: =IF(ISBLANK(A53), "", YEAR(B53)) -> 2024 | K53: =IF(ISBLANK(A53), "", CONCATENATE(J53," - ",I53)) -> 2024 - 8
A54: 53 | B54: 45522 | C54: Split Return | D54: Others | E54: 2400 | F54: =IF(ISBLANK(A54),"", F53+E54) -> 13654.85 | G54: Mafaaz | H54: G3 | I54: =IF(ISBLANK(A54), "", MONTH(B54)) -> 8 | J54: =IF(ISBLANK(A54), "", YEAR(B54)) -> 2024 | K54: =IF(ISBLANK(A54), "", CONCATENATE(J54," - ",I54)) -> 2024 - 8
A55: 54 | B55: 45522 | C55: Split Return | D55: Others | E55: 325 | F55: =IF(ISBLANK(A55),"", F54+E55) -> 13979.85 | G55: Mohit | H55: G3 | I55: =IF(ISBLANK(A55), "", MONTH(B55)) -> 8 | J55: =IF(ISBLANK(A55), "", YEAR(B55)) -> 2024 | K55: =IF(ISBLANK(A55), "", CONCATENATE(J55," - ",I55)) -> 2024 - 8
A56: 55 | B56: 45522 | C56: Split Return | D56: Others | E56: 435 | F56: =IF(ISBLANK(A56),"", F55+E56) -> 14414.85 | G56: Snehith | H56: G3 | I56: =IF(ISBLANK(A56), "", MONTH(B56)) -> 8 | J56: =IF(ISBLANK(A56), "", YEAR(B56)) -> 2024 | K56: =IF(ISBLANK(A56), "", CONCATENATE(J56," - ",I56)) -> 2024 - 8
A57: 56 | B57: 45522 | C57: Split Return | D57: Others | E57: 860 | F57: =IF(ISBLANK(A57),"", F56+E57) -> 15274.85 | G57: Harshit + Himannshu | H57: G3 | I57: =IF(ISBLANK(A57), "", MONTH(B57)) -> 8 | J57: =IF(ISBLANK(A57), "", YEAR(B57)) -> 2024 | K57: =IF(ISBLANK(A57), "", CONCATENATE(J57," - ",I57)) -> 2024 - 8
A58: 57 | B58: 45522 | C58: Travel | D58: Personal, Others | E58: -364 | F58: =IF(ISBLANK(A58),"", F57+E58) -> 14910.85 | G58: Cab | H58: G4 | I58: =IF(ISBLANK(A58), "", MONTH(B58)) -> 8 | J58: =IF(ISBLANK(A58), "", YEAR(B58)) -> 2024 | K58: =IF(ISBLANK(A58), "", CONCATENATE(J58," - ",I58)) -> 2024 - 8
A59: 58 | B59: 45522 | C59: Fun | D59: Personal, Others | E59: -2700 | F59: =IF(ISBLANK(A59),"", F58+E59) -> 12210.85 | G59: Go Cart | H59: G4 | I59: =IF(ISBLANK(A59), "", MONTH(B59)) -> 8 | J59: =IF(ISBLANK(A59), "", YEAR(B59)) -> 2024 | K59: =IF(ISBLANK(A59), "", CONCATENATE(J59," - ",I59)) -> 2024 - 8
A60: 59 | B60: 45522 | C60: Travel | D60: Personal | E60: -570 | F60: =IF(ISBLANK(A60),"", F59+E60) -> 11640.85 | G60: Cab | I60: =IF(ISBLANK(A60), "", MONTH(B60)) -> 8 | J60: =IF(ISBLANK(A60), "", YEAR(B60)) -> 2024 | K60: =IF(ISBLANK(A60), "", CONCATENATE(J60," - ",I60)) -> 2024 - 8
A61: 60 | B61: 45522 | C61: Food | D61: Personal, Others | E61: -1894 | F61: =IF(ISBLANK(A61),"", F60+E61) -> 9746.85 | G61: Biryani Lunch | H61: G4 | I61: =IF(ISBLANK(A61), "", MONTH(B61)) -> 8 | J61: =IF(ISBLANK(A61), "", YEAR(B61)) -> 2024 | K61: =IF(ISBLANK(A61), "", CONCATENATE(J61," - ",I61)) -> 2024 - 8
A62: 61 | B62: 45522 | C62: Travel | D62: Personal, Others | E62: -360 | F62: =IF(ISBLANK(A62),"", F61+E62) -> 9386.85 | G62: Cab | H62: G4 | I62: =IF(ISBLANK(A62), "", MONTH(B62)) -> 8 | J62: =IF(ISBLANK(A62), "", YEAR(B62)) -> 2024 | K62: =IF(ISBLANK(A62), "", CONCATENATE(J62," - ",I62)) -> 2024 - 8
A63: 62 | B63: 45522 | C63: Travel | D63: Personal, Others | E63: -237 | F63: =IF(ISBLANK(A63),"", F62+E63) -> 9149.85 | G63: Cab | H63: G4 | I63: =IF(ISBLANK(A63), "", MONTH(B63)) -> 8 | J63: =IF(ISBLANK(A63), "", YEAR(B63)) -> 2024 | K63: =IF(ISBLANK(A63), "", CONCATENATE(J63," - ",I63)) -> 2024 - 8
A64: 63 | B64: 45522 | C64: Travel | D64: Personal, Others | E64: -475 | F64: =IF(ISBLANK(A64),"", F63+E64) -> 8674.85 | G64: Cab | H64: G4 | I64: =IF(ISBLANK(A64), "", MONTH(B64)) -> 8 | J64: =IF(ISBLANK(A64), "", YEAR(B64)) -> 2024 | K64: =IF(ISBLANK(A64), "", CONCATENATE(J64," - ",I64)) -> 2024 - 8
A65: 64 | B65: 45522 | C65: Shop | D65: Personal | E65: -1215 | F65: =IF(ISBLANK(A65),"", F64+E65) -> 7459.85 | G65: Shorts + Milk | I65: =IF(ISBLANK(A65), "", MONTH(B65)) -> 8 | J65: =IF(ISBLANK(A65), "", YEAR(B65)) -> 2024 | K65: =IF(ISBLANK(A65), "", CONCATENATE(J65," - ",I65)) -> 2024 - 8
A66: 65 | B66: 45522 | C66: Split Return | D66: Others | E66: 165 | F66: =IF(ISBLANK(A66),"", F65+E66) -> 7624.85 | G66: Rishabh | H66: G5 | I66: =IF(ISBLANK(A66), "", MONTH(B66)) -> 8 | J66: =IF(ISBLANK(A66), "", YEAR(B66)) -> 2024 | K66: =IF(ISBLANK(A66), "", CONCATENATE(J66," - ",I66)) -> 2024 - 8
A67: 66 | B67: 45523 | C67: Split Return | D67: Others | E67: 4800 | F67: =IF(ISBLANK(A67),"", F66+E67) -> 12424.85 | G67: Manit | H67: G1 / G4 / G7 | I67: =IF(ISBLANK(A67), "", MONTH(B67)) -> 8 | J67: =IF(ISBLANK(A67), "", YEAR(B67)) -> 2024 | K67: =IF(ISBLANK(A67), "", CONCATENATE(J67," - ",I67)) -> 2024 - 8
A68: 67 | B68: 45523 | C68: Split Return | D68: Others | E68: 6350 | F68: =IF(ISBLANK(A68),"", F67+E68) -> 18774.85 | G68: Bhavye | H68: G1 / G2 / G4 / G5 / G7 | I68: =IF(ISBLANK(A68), "", MONTH(B68)) -> 8 | J68: =IF(ISBLANK(A68), "", YEAR(B68)) -> 2024 | K68: =IF(ISBLANK(A68), "", CONCATENATE(J68," - ",I68)) -> 2024 - 8
A69: 68 | B69: 45523 | C69: Food | D69: Personal | E69: -330 | F69: =IF(ISBLANK(A69),"", F68+E69) -> 18444.85 | G69: Airport Coffee | I69: =IF(ISBLANK(A69), "", MONTH(B69)) -> 8 | J69: =IF(ISBLANK(A69), "", YEAR(B69)) -> 2024 | K69: =IF(ISBLANK(A69), "", CONCATENATE(J69," - ",I69)) -> 2024 - 8
A70: 69 | B70: 45523 | C70: Travel | D70: Personal | E70: -30 | F70: =IF(ISBLANK(A70),"", F69+E70) -> 18414.85 | G70: Metro | I70: =IF(ISBLANK(A70), "", MONTH(B70)) -> 8 | J70: =IF(ISBLANK(A70), "", YEAR(B70)) -> 2024 | K70: =IF(ISBLANK(A70), "", CONCATENATE(J70," - ",I70)) -> 2024 - 8
A71: 70 | B71: 45523 | C71: Travel | D71: Personal | E71: -60 | F71: =IF(ISBLANK(A71),"", F70+E71) -> 18354.85 | G71: Metro | I71: =IF(ISBLANK(A71), "", MONTH(B71)) -> 8 | J71: =IF(ISBLANK(A71), "", YEAR(B71)) -> 2024 | K71: =IF(ISBLANK(A71), "", CONCATENATE(J71," - ",I71)) -> 2024 - 8
A72: 71 | B72: 45523 | C72: Split Return | D72: Others | E72: 3400 | F72: =IF(ISBLANK(A72),"", F71+E72) -> 21754.85 | G72: Sarthak | H72: G1 / G7 | I72: =IF(ISBLANK(A72), "", MONTH(B72)) -> 8 | J72: =IF(ISBLANK(A72), "", YEAR(B72)) -> 2024 | K72: =IF(ISBLANK(A72), "", CONCATENATE(J72," - ",I72)) -> 2024 - 8
A73: 72 | B73: 45523 | C73: Split Return | D73: Others | E73: 1290 | F73: =IF(ISBLANK(A73),"", F72+E73) -> 23044.85 | G73: Gautam | H73: G7 | I73: =IF(ISBLANK(A73), "", MONTH(B73)) -> 8 | J73: =IF(ISBLANK(A73), "", YEAR(B73)) -> 2024 | K73: =IF(ISBLANK(A73), "", CONCATENATE(J73," - ",I73)) -> 2024 - 8
A74: 73 | B74: 45523 | C74: Travel | D74: Personal | E74: -30 | F74: =IF(ISBLANK(A74),"", F73+E74) -> 23014.85 | G74: Metro | I74: =IF(ISBLANK(A74), "", MONTH(B74)) -> 8 | J74: =IF(ISBLANK(A74), "", YEAR(B74)) -> 2024 | K74: =IF(ISBLANK(A74), "", CONCATENATE(J74," - ",I74)) -> 2024 - 8
A75: 74 | B75: 45523 | C75: Travel | D75: Personal | E75: -50 | F75: =IF(ISBLANK(A75),"", F74+E75) -> 22964.85 | G75: Auto | I75: =IF(ISBLANK(A75), "", MONTH(B75)) -> 8 | J75: =IF(ISBLANK(A75), "", YEAR(B75)) -> 2024 | K75: =IF(ISBLANK(A75), "", CONCATENATE(J75," - ",I75)) -> 2024 - 8
A76: 75 | B76: 45524 | C76: Tax Return | D76: Personal | E76: 52130 | F76: =IF(ISBLANK(A76),"", F75+E76) -> 75094.85 | G76: FY 23-24 | I76: =IF(ISBLANK(A76), "", MONTH(B76)) -> 8 | J76: =IF(ISBLANK(A76), "", YEAR(B76)) -> 2024 | K76: =IF(ISBLANK(A76), "", CONCATENATE(J76," - ",I76)) -> 2024 - 8
A77: 76 | B77: 45524 | C77: SIP | D77: Personal | E77: -5000 | F77: =IF(ISBLANK(A77),"", F76+E77) -> 70094.85 | I77: =IF(ISBLANK(A77), "", MONTH(B77)) -> 8 | J77: =IF(ISBLANK(A77), "", YEAR(B77)) -> 2024 | K77: =IF(ISBLANK(A77), "", CONCATENATE(J77," - ",I77)) -> 2024 - 8
A78: 77 | B78: 45525 | C78: Monthly Bill | D78: Personal | E78: -2002.46 | F78: =IF(ISBLANK(A78),"", F77+E78) -> 68092.39 | G78: Phone + Wifi | I78: =IF(ISBLANK(A78), "", MONTH(B78)) -> 8 | J78: =IF(ISBLANK(A78), "", YEAR(B78)) -> 2024 | K78: =IF(ISBLANK(A78), "", CONCATENATE(J78," - ",I78)) -> 2024 - 8
A79: 78 | B79: 45525 | C79: Travel | D79: Personal | E79: -50 | F79: =IF(ISBLANK(A79),"", F78+E79) -> 68042.39 | G79: Metro | I79: =IF(ISBLANK(A79), "", MONTH(B79)) -> 8 | J79: =IF(ISBLANK(A79), "", YEAR(B79)) -> 2024 | K79: =IF(ISBLANK(A79), "", CONCATENATE(J79," - ",I79)) -> 2024 - 8
A80: 79 | B80: 45525 | C80: Shop | D80: Personal | E80: -3980 | F80: =IF(ISBLANK(A80),"", F79+E80) -> 64062.39 | G80: Uniqlo | I80: =IF(ISBLANK(A80), "", MONTH(B80)) -> 8 | J80: =IF(ISBLANK(A80), "", YEAR(B80)) -> 2024 | K80: =IF(ISBLANK(A80), "", CONCATENATE(J80," - ",I80)) -> 2024 - 8
A81: 80 | B81: 45525 | C81: Shop | D81: Others | E81: -5540 | F81: =IF(ISBLANK(A81),"", F80+E81) -> 58522.39 | G81: Tamanna | H81: G9 | I81: =IF(ISBLANK(A81), "", MONTH(B81)) -> 8 | J81: =IF(ISBLANK(A81), "", YEAR(B81)) -> 2024 | K81: =IF(ISBLANK(A81), "", CONCATENATE(J81," - ",I81)) -> 2024 - 8
A82: 81 | B82: 45525 | C82: Split Return | D82: Others | E82: 3000 | F82: =IF(ISBLANK(A82),"", F81+E82) -> 61522.39 | G82: Tamanna | H82: G9 | I82: =IF(ISBLANK(A82), "", MONTH(B82)) -> 8 | J82: =IF(ISBLANK(A82), "", YEAR(B82)) -> 2024 | K82: =IF(ISBLANK(A82), "", CONCATENATE(J82," - ",I82)) -> 2024 - 8
A83: 82 | B83: 45525 | C83: Travel | D83: Personal | E83: -134 | F83: =IF(ISBLANK(A83),"", F82+E83) -> 61388.39 | G83: Auto | I83: =IF(ISBLANK(A83), "", MONTH(B83)) -> 8 | J83: =IF(ISBLANK(A83), "", YEAR(B83)) -> 2024 | K83: =IF(ISBLANK(A83), "", CONCATENATE(J83," - ",I83)) -> 2024 - 8
A84: 83 | B84: 45525 | C84: Food | D84: Personal, Others | E84: -1533 | F84: =IF(ISBLANK(A84),"", F83+E84) -> 59855.39 | G84: PVR | I84: =IF(ISBLANK(A84), "", MONTH(B84)) -> 8 | J84: =IF(ISBLANK(A84), "", YEAR(B84)) -> 2024 | K84: =IF(ISBLANK(A84), "", CONCATENATE(J84," - ",I84)) -> 2024 - 8
A85: 84 | B85: 45525 | C85: Travel | D85: Personal | E85: -76 | F85: =IF(ISBLANK(A85),"", F84+E85) -> 59779.39 | G85: Auto | I85: =IF(ISBLANK(A85), "", MONTH(B85)) -> 8 | J85: =IF(ISBLANK(A85), "", YEAR(B85)) -> 2024 | K85: =IF(ISBLANK(A85), "", CONCATENATE(J85," - ",I85)) -> 2024 - 8
A86: 85 | B86: 45525 | C86: Travel | D86: Personal, Others | E86: -27.59 | F86: =IF(ISBLANK(A86),"", F85+E86) -> 59751.8 | G86: Auto | I86: =IF(ISBLANK(A86), "", MONTH(B86)) -> 8 | J86: =IF(ISBLANK(A86), "", YEAR(B86)) -> 2024 | K86: =IF(ISBLANK(A86), "", CONCATENATE(J86," - ",I86)) -> 2024 - 8
A87: 86 | B87: 45525 | C87: Travel | D87: Personal | E87: -83.9 | F87: =IF(ISBLANK(A87),"", F86+E87) -> 59667.9 | G87: Auto | I87: =IF(ISBLANK(A87), "", MONTH(B87)) -> 8 | J87: =IF(ISBLANK(A87), "", YEAR(B87)) -> 2024 | K87: =IF(ISBLANK(A87), "", CONCATENATE(J87," - ",I87)) -> 2024 - 8
A88: 87 | B88: 45526 | C88: Travel | D88: Personal | E88: -40 | F88: =IF(ISBLANK(A88),"", F87+E88) -> 59627.9 | G88: Metro | I88: =IF(ISBLANK(A88), "", MONTH(B88)) -> 8 | J88: =IF(ISBLANK(A88), "", YEAR(B88)) -> 2024 | K88: =IF(ISBLANK(A88), "", CONCATENATE(J88," - ",I88)) -> 2024 - 8
A89: 88 | B89: 45526 | C89: Travel | D89: Personal | E89: -40 | F89: =IF(ISBLANK(A89),"", F88+E89) -> 59587.9 | G89: Metro | I89: =IF(ISBLANK(A89), "", MONTH(B89)) -> 8 | J89: =IF(ISBLANK(A89), "", YEAR(B89)) -> 2024 | K89: =IF(ISBLANK(A89), "", CONCATENATE(J89," - ",I89)) -> 2024 - 8
A90: 89 | B90: 45526 | C90: Food | D90: Personal | E90: -397 | F90: =IF(ISBLANK(A90),"", F89+E90) -> 59190.9 | G90: Train Pizza | I90: =IF(ISBLANK(A90), "", MONTH(B90)) -> 8 | J90: =IF(ISBLANK(A90), "", YEAR(B90)) -> 2024 | K90: =IF(ISBLANK(A90), "", CONCATENATE(J90," - ",I90)) -> 2024 - 8
A91: 90 | B91: 45526 | C91: Food | D91: Personal, Others | E91: -632.58 | F91: =IF(ISBLANK(A91),"", F90+E91) -> 58558.32 | G91: Muskan Samosa Party | I91: =IF(ISBLANK(A91), "", MONTH(B91)) -> 8 | J91: =IF(ISBLANK(A91), "", YEAR(B91)) -> 2024 | K91: =IF(ISBLANK(A91), "", CONCATENATE(J91," - ",I91)) -> 2024 - 8
A92: 91 | B92: 45526 | C92: Travel | D92: Personal | E92: -184 | F92: =IF(ISBLANK(A92),"", F91+E92) -> 58374.32 | G92: Auto | I92: =IF(ISBLANK(A92), "", MONTH(B92)) -> 8 | J92: =IF(ISBLANK(A92), "", YEAR(B92)) -> 2024 | K92: =IF(ISBLANK(A92), "", CONCATENATE(J92," - ",I92)) -> 2024 - 8
A93: 92 | B93: 45526 | C93: Monthly Bill | D93: Family | E93: -700 | F93: =IF(ISBLANK(A93),"", F92+E93) -> 57674.32 | G93: TV | I93: =IF(ISBLANK(A93), "", MONTH(B93)) -> 8 | J93: =IF(ISBLANK(A93), "", YEAR(B93)) -> 2024 | K93: =IF(ISBLANK(A93), "", CONCATENATE(J93," - ",I93)) -> 2024 - 8
A94: 93 | B94: 45527 | C94: Split Return | D94: Others | E94: 725 | F94: =IF(ISBLANK(A94),"", F93+E94) -> 58399.32 | G94: Hannah | I94: =IF(ISBLANK(A94), "", MONTH(B94)) -> 8 | J94: =IF(ISBLANK(A94), "", YEAR(B94)) -> 2024 | K94: =IF(ISBLANK(A94), "", CONCATENATE(J94," - ",I94)) -> 2024 - 8
... A102: 101 | B102: 45532 | C102: Food | D102: Family | E102: -564.63 | F102: =IF(ISBLANK(A102),"", F101+E102) -> 55526.69 | G102: Lunch | I102: =IF(ISBLANK(A102), "", MONTH(B102)) -> 8 | J102: =IF(ISBLANK(A102), "", YEAR(B102)) -> 2024 | K102: =IF(ISBLANK(A102), "", CONCATENATE(J102," - ",I102)) -> 2024 - 8
A103: 102 | B103: 45533 | C103: Misc | D103: Others | E103: -200 | F103: =IF(ISBLANK(A103),"", F102+E103) -> 55326.69 | I103: =IF(ISBLANK(A103), "", MONTH(B103)) -> 8 | J103: =IF(ISBLANK(A103), "", YEAR(B103)) -> 2024 | K103: =IF(ISBLANK(A103), "", CONCATENATE(J103," - ",I103)) -> 2024 - 8
A104: 103 | B104: 45533 | C104: Food | D104: Family | E104: -2331 | F104: =IF(ISBLANK(A104),"", F103+E104) -> 52995.69 | G104: Farzi Cafe | I104: =IF(ISBLANK(A104), "", MONTH(B104)) -> 8 | J104: =IF(ISBLANK(A104), "", YEAR(B104)) -> 2024 | K104: =IF(ISBLANK(A104), "", CONCATENATE(J104," - ",I104)) -> 2024 - 8
A105: 104 | B105: 45534 | C105: Food | D105: Family | E105: -200 | F105: =IF(ISBLANK(A105),"", F104+E105) -> 52795.69 | G105: Airport | I105: =IF(ISBLANK(A105), "", MONTH(B105)) -> 8 | J105: =IF(ISBLANK(A105), "", YEAR(B105)) -> 2024 | K105: =IF(ISBLANK(A105), "", CONCATENATE(J105," - ",I105)) -> 2024 - 8
A106: 105 | B106: 45534 | C106: SIP | D106: Personal | E106: -1000 | F106: =IF(ISBLANK(A106),"", F105+E106) -> 51795.69 | I106: =IF(ISBLANK(A106), "", MONTH(B106)) -> 8 | J106: =IF(ISBLANK(A106), "", YEAR(B106)) -> 2024 | K106: =IF(ISBLANK(A106), "", CONCATENATE(J106," - ",I106)) -> 2024 - 8
A107: 106 | B107: 45535 | C107: Shop | D107: Family | E107: -581 | F107: =IF(ISBLANK(A107),"", F106+E107) -> 51214.69 | I107: =IF(ISBLANK(A107), "", MONTH(B107)) -> 8 | J107: =IF(ISBLANK(A107), "", YEAR(B107)) -> 2024 | K107: =IF(ISBLANK(A107), "", CONCATENATE(J107," - ",I107)) -> 2024 - 8
A108: 107 | B108: 45535 | C108: Travel | D108: Family | E108: -196 | F108: =IF(ISBLANK(A108),"", F107+E108) -> 51018.69 | G108: Auto | I108: =IF(ISBLANK(A108), "", MONTH(B108)) -> 8 | J108: =IF(ISBLANK(A108), "", YEAR(B108)) -> 2024 | K108: =IF(ISBLANK(A108), "", CONCATENATE(J108," - ",I108)) -> 2024 - 8
A109: 108 | B109: 45535 | C109: Travel | D109: Family | E109: -156.75 | F109: =IF(ISBLANK(A109),"", F108+E109) -> 50861.94 | G109: Metro | I109: =IF(ISBLANK(A109), "", MONTH(B109)) -> 8 | J109: =IF(ISBLANK(A109), "", YEAR(B109)) -> 2024 | K109: =IF(ISBLANK(A109), "", CONCATENATE(J109," - ",I109)) -> 2024 - 8
A110: 109 | B110: 45535 | C110: Food | D110: Family | E110: -641 | F110: =IF(ISBLANK(A110),"", F109+E110) -> 50220.94 | G110: Ice Cream | I110: =IF(ISBLANK(A110), "", MONTH(B110)) -> 8 | J110: =IF(ISBLANK(A110), "", YEAR(B110)) -> 2024 | K110: =IF(ISBLANK(A110), "", CONCATENATE(J110," - ",I110)) -> 2024 - 8
A111: 110 | B111: 45535 | C111: Shop | D111: Family | E111: -5101 | F111: =IF(ISBLANK(A111),"", F110+E111) -> 45119.94 | G111: Clothes | I111: =IF(ISBLANK(A111), "", MONTH(B111)) -> 8 | J111: =IF(ISBLANK(A111), "", YEAR(B111)) -> 2024 | K111: =IF(ISBLANK(A111), "", CONCATENATE(J111," - ",I111)) -> 2024 - 8
A112: 111 | B112: 45535 | C112: Shop | D112: Family | E112: -1113 | F112: =IF(ISBLANK(A112),"", F111+E112) -> 44006.94 | G112: Utensils | I112: =IF(ISBLANK(A112), "", MONTH(B112)) -> 8 | J112: =IF(ISBLANK(A112), "", YEAR(B112)) -> 2024 | K112: =IF(ISBLANK(A112), "", CONCATENATE(J112," - ",I112)) -> 2024 - 8
...

Sheet Chart Table
A1: Year | B1: Month | C1: Unique Ref | D1: Fuel | E1: Travel | F1: SIP | G1: Misc | H1: Lend | I1: Fun | J1: Transfer | K1: Shop | L1: Food | M1: Monthly Bill | N1: Yearly Bill | O1: Rent | P1: Medicine | Q1: Lend Return | R1: Split Return | S1: Salary | T1: Tax Return | U1: Cashback | V1: Starter | W1: Total Debit | X1: Total Credit | Y1: Desert
A2: =IFERROR(__xludf.DUMMYFUNCTION("SPLIT(C2, "" - "")"),2024.0) -> 2024 | B2: =IFERROR(__xludf.DUMMYFUNCTION("""COMPUTED_VALUE"""),8.0) -> 8 | C2: {=UNIQUE(Main!K2:K1000)} -> 2024 - 8 | D2: =SUMIFS(Main!$E$2:$E1000,Main!$I$2:$I1000, "="&$B2, Main!$J$2:$J1000, "="&$A2, Main!$C$2:$C1000, "="&D$1) -> -393.91 | E2: =SUMIFS(Main!$E$2:$E1000,Main!$I$2:$I1000, "="&$B2, Main!$J$2:$J1000, "="&$A2, Main!$C$2:$C1000, "="&E$1) -> -5985.39 | F2: =SUMIFS(Main!$E$2:$E1000,Main!$I$2:$I1000, "="&$B2, Main!$J$2:$J1000, "="&$A2, Main!$C$2:$C1000, "="&F$1) -> -6000 | G2: =SUMIFS(Main!$E$2:$E1000,Main!$I$2:$I1000, "="&$B2, Main!$J$2:$J1000, "="&$A2, Main!$C$2:$C1000, "="&G$1) -> -875 | H2: =SUMIFS(Main!$E$2:$E1000,Main!$I$2:$I1000, "="&$B2, Main!$J$2:$J1000, "="&$A2, Main!$C$2:$C1000, "="&H$1) -> -1500 | I2: =SUMIFS(Main!$E$2:$E1000,Main!$I$2:$I1000, "="&$B2, Main!$J$2:$J1000, "="&$A2, Main!$C$2:$C1000, "="&I$1) -> -10696 | J2: =SUMIFS(Main!$E$2:$E1000,Main!$I$2:$I1000, "="&$B2, Main!$J$2:$J1000, "="&$A2, Main!$C$2:$C1000, "="&J$1) -> -45000 | K2: =SUMIFS(Main!$E$2:$E1000,Main!$I$2:$I1000, "="&$B2, Main!$J$2:$J1000, "="&$A2, Main!$C$2:$C1000, "="&K$1) -> -46605 | ... U2: =SUMIFS(Main!$E$2:$E1000,Main!$I$2:$I1000, "="&$B2, Main!$J$2:$J1000, "="&$A2, Main!$C$2:$C1000, "="&U$1) -> 0 | V2: =101276.91 -> 101276.91 | W2: =SUMIF($B2:$U2, "<0") -> -147663.97 | X2: =SUMIF($B2:$U2, ">0") -> 86509 | Y2: =V2+W2+X2 -> 40121.94
A3: =IFERROR(__xludf.DUMMYFUNCTION("SPLIT(C3, "" - "")"),2024.0) -> 2024 | B3: =IFERROR(__xludf.DUMMYFUNCTION("""COMPUTED_VALUE"""),9.0) -> 9 | C3: 2024 - 9 | D3: =SUMIFS(Main!$E$2:$E1000,Main!$I$2:$I1000, "="&$B3, Main!$J$2:$J1000, "="&$A3, Main!$C$2:$C1000, "="&D$1) -> -1879.7 | E3: =SUMIFS(Main!$E$2:$E1000,Main!$I$2:$I1000, "="&$B3, Main!$J$2:$J1000, "="&$A3, Main!$C$2:$C1000, "="&E$1) -> -1142.17 | F3: =SUMIFS(Main!$E$2:$E1000,Main!$I$2:$I1000, "="&$B3, Main!$J$2:$J1000, "="&$A3, Main!$C$2:$C1000, "="&F$1) -> -2000 | G3: =SUMIFS(Main!$E$2:$E1000,Main!$I$2:$I1000, "="&$B3, Main!$J$2:$J1000, "="&$A3, Main!$C$2:$C1000, "="&G$1) -> -1481 | H3: =SUMIFS(Main!$E$2:$E1000,Main!$I$2:$I1000, "="&$B3, Main!$J$2:$J1000, "="&$A3, Main!$C$2:$C1000, "="&H$1) -> 0 | I3: =SUMIFS(Main!$E$2:$E1000,Main!$I$2:$I1000, "="&$B3, Main!$J$2:$J1000, "="&$A3, Main!$C$2:$C1000, "="&I$1) -> -1141.6 | J3: =SUMIFS(Main!$E$2:$E1000,Main!$I$2:$I1000, "="&$B3, Main!$J$2:$J1000, "="&$A3, Main!$C$2:$C1000, "="&J$1) -> -100000 | K3: =SUMIFS(Main!$E$2:$E1000,Main!$I$2:$I1000, "="&$B3, Main!$J$2:$J1000, "="&$A3, Main!$C$2:$C1000, "="&K$1) -> -3508 | ... U3: =SUMIFS(Main!$E$2:$E1000,Main!$I$2:$I1000, "="&$B3, Main!$J$2:$J1000, "="&$A3, Main!$C$2:$C1000, "="&U$1) -> 0 | V3: =Y2 -> 40121.94 | W3: =SUMIF($B3:$U3, "<0") -> -124809.43 | X3: =SUMIF($B3:$U3, ">0") -> 115554.08 | Y3: =V3+W3+X3 -> 30866.59
A4: =IFERROR(__xludf.DUMMYFUNCTION("SPLIT(C4, "" - "")"),2024.0) -> 2024 | B4: =IFERROR(__xludf.DUMMYFUNCTION("""COMPUTED_VALUE"""),10.0) -> 10 | C4: 2024 - 10 | D4: =SUMIFS(Main!$E$2:$E1000,Main!$I$2:$I1000, "="&$B4, Main!$J$2:$J1000, "="&$A4, Main!$C$2:$C1000, "="&D$1) -> -321.95 | E4: =SUMIFS(Main!$E$2:$E1000,Main!$I$2:$I1000, "="&$B4, Main!$J$2:$J1000, "="&$A4, Main!$C$2:$C1000, "="&E$1) -> -29124 | F4: =SUMIFS(Main!$E$2:$E1000,Main!$I$2:$I1000, "="&$B4, Main!$J$2:$J1000, "="&$A4, Main!$C$2:$C1000, "="&F$1) -> -2100 | G4: =SUMIFS(Main!$E$2:$E1000,Main!$I$2:$I1000, "="&$B4, Main!$J$2:$J1000, "="&$A4, Main!$C$2:$C1000, "="&G$1) -> -600 | H4: =SUMIFS(Main!$E$2:$E1000,Main!$I$2:$I1000, "="&$B4, Main!$J$2:$J1000, "="&$A4, Main!$C$2:$C1000, "="&H$1) -> -59 | I4: =SUMIFS(Main!$E$2:$E1000,Main!$I$2:$I1000, "="&$B4, Main!$J$2:$J1000, "="&$A4, Main!$C$2:$C1000, "="&I$1) -> -16212.84 | J4: =SUMIFS(Main!$E$2:$E1000,Main!$I$2:$I1000, "="&$B4, Main!$J$2:$J1000, "="&$A4, Main!$C$2:$C1000, "="&J$1) -> -25000 | K4: =SUMIFS(Main!$E$2:$E1000,Main!$I$2:$I1000, "="&$B4, Main!$J$2:$J1000, "="&$A4, Main!$C$2:$C1000, "="&K$1) -> -36363.39 | ... U4: =SUMIFS(Main!$E$2:$E1000,Main!$I$2:$I1000, "="&$B4, Main!$J$2:$J1000, "="&$A4, Main!$C$2:$C1000, "="&U$1) -> 0 | V4: =Y3 -> 30866.59 | W4: =SUMIF($B4:$U4, "<0") -> -116748.72 | X4: =SUMIF($B4:$U4, ">0") -> 86015.53 | Y4: =V4+W4+X4 -> 133.4
A5: =IFERROR(__xludf.DUMMYFUNCTION("SPLIT(C5, "" - "")"),2024.0) -> 2024 | B5: =IFERROR(__xludf.DUMMYFUNCTION("""COMPUTED_VALUE"""),11.0) -> 11 | C5: 2024 - 11 | D5: =SUMIFS(Main!$E$2:$E1000,Main!$I$2:$I1000, "="&$B5, Main!$J$2:$J1000, "="&$A5, Main!$C$2:$C1000, "="&D$1) -> 0 | E5: =SUMIFS(Main!$E$2:$E1000,Main!$I$2:$I1000, "="&$B5, Main!$J$2:$J1000, "="&$A5, Main!$C$2:$C1000, "="&E$1) -> -87 | F5: =SUMIFS(Main!$E$2:$E1000,Main!$I$2:$I1000, "="&$B5, Main!$J$2:$J1000, "="&$A5, Main!$C$2:$C1000, "="&F$1) -> -2100 | G5: =SUMIFS(Main!$E$2:$E1000,Main!$I$2:$I1000, "="&$B5, Main!$J$2:$J1000, "="&$A5, Main!$C$2:$C1000, "="&G$1) -> -1527 | H5: =SUMIFS(Main!$E$2:$E1000,Main!$I$2:$I1000, "="&$B5, Main!$J$2:$J1000, "="&$A5, Main!$C$2:$C1000, "="&H$1) -> -11059 | I5: =SUMIFS(Main!$E$2:$E1000,Main!$I$2:$I1000, "="&$B5, Main!$J$2:$J1000, "="&$A5, Main!$C$2:$C1000, "="&I$1) -> -31609 | J5: =SUMIFS(Main!$E$2:$E1000,Main!$I$2:$I1000, "="&$B5, Main!$J$2:$J1000, "="&$A5, Main!$C$2:$C1000, "="&J$1) -> -14000 | K5: =SUMIFS(Main!$E$2:$E1000,Main!$I$2:$I1000, "="&$B5, Main!$J$2:$J1000, "="&$A5, Main!$C$2:$C1000, "="&K$1) -> -12806.64 | ... U5: =SUMIFS(Main!$E$2:$E1000,Main!$I$2:$I1000, "="&$B5, Main!$J$2:$J1000, "="&$A5, Main!$C$2:$C1000, "="&U$1) -> 0 | V5: =Y4 -> 133.4 | W5: =SUMIF($B5:$U5, "<0") -> -79312.3 | X5: =SUMIF($B5:$U5, ">0") -> 81134 | Y5: =V5+W5+X5 -> 1955.1
A6: =IFERROR(__xludf.DUMMYFUNCTION("SPLIT(C6, "" - "")"),2024.0) -> 2024 | B6: =IFERROR(__xludf.DUMMYFUNCTION("""COMPUTED_VALUE"""),12.0) -> 12 | C6: 2024 - 12 | D6: =SUMIFS(Main!$E$2:$E1000,Main!$I$2:$I1000, "="&$B6, Main!$J$2:$J1000, "="&$A6, Main!$C$2:$C1000, "="&D$1) -> -300 | E6: =SUMIFS(Main!$E$2:$E1000,Main!$I$2:$I1000, "="&$B6, Main!$J$2:$J1000, "="&$A6, Main!$C$2:$C1000, "="&E$1) -> -93 | F6: =SUMIFS(Main!$E$2:$E1000,Main!$I$2:$I1000, "="&$B6, Main!$J$2:$J1000, "="&$A6, Main!$C$2:$C1000, "="&F$1) -> 17060.19 | G6: =SUMIFS(Main!$E$2:$E1000,Main!$I$2:$I1000, "="&$B6, Main!$J$2:$J1000, "="&$A6, Main!$C$2:$C1000, "="&G$1) -> -9394 | H6: =SUMIFS(Main!$E$2:$E1000,Main!$I$2:$I1000, "="&$B6, Main!$J$2:$J1000, "="&$A6, Main!$C$2:$C1000, "="&H$1) -> -10000 | I6: =SUMIFS(Main!$E$2:$E1000,Main!$I$2:$I1000, "="&$B6, Main!$J$2:$J1000, "="&$A6, Main!$C$2:$C1000, "="&I$1) -> -3200 | J6: =SUMIFS(Main!$E$2:$E1000,Main!$I$2:$I1000, "="&$B6, Main!$J$2:$J1000, "="&$A6, Main!$C$2:$C1000, "="&J$1) -> -40000 | K6: =SUMIFS(Main!$E$2:$E1000,Main!$I$2:$I1000, "="&$B6, Main!$J$2:$J1000, "="&$A6, Main!$C$2:$C1000, "="&K$1) -> -32963.05 | ... U6: =SUMIFS(Main!$E$2:$E1000,Main!$I$2:$I1000, "="&$B6, Main!$J$2:$J1000, "="&$A6, Main!$C$2:$C1000, "="&U$1) -> 0 | V6: =Y5 -> 1955.1 | W6: =SUMIF($B6:$U6, "<0") -> -106172.51 | X6: =SUMIF($B6:$U6, ">0") -> 202885.19 | Y6: =V6+W6+X6 -> 98667.78
A7: =IFERROR(__xludf.DUMMYFUNCTION("SPLIT(C7, "" - "")"),2025.0) -> 2025 | B7: =IFERROR(__xludf.DUMMYFUNCTION("""COMPUTED_VALUE"""),1.0) -> 1 | C7: 2025 - 1 | D7: =SUMIFS(Main!$E$2:$E1000,Main!$I$2:$I1000, "="&$B7, Main!$J$2:$J1000, "="&$A7, Main!$C$2:$C1000, "="&D$1) -> -617.99 | E7: =SUMIFS(Main!$E$2:$E1000,Main!$I$2:$I1000, "="&$B7, Main!$J$2:$J1000, "="&$A7, Main!$C$2:$C1000, "="&E$1) -> -1427.85 | F7: =SUMIFS(Main!$E$2:$E1000,Main!$I$2:$I1000, "="&$B7, Main!$J$2:$J1000, "="&$A7, Main!$C$2:$C1000, "="&F$1) -> 0 | G7: =SUMIFS(Main!$E$2:$E1000,Main!$I$2:$I1000, "="&$B7, Main!$J$2:$J1000, "="&$A7, Main!$C$2:$C1000, "="&G$1) -> -8766.66 | H7: =SUMIFS(Main!$E$2:$E1000,Main!$I$2:$I1000, "="&$B7, Main!$J$2:$J1000, "="&$A7, Main!$C$2:$C1000, "="&H$1) -> 0 | I7: =SUMIFS(Main!$E$2:$E1000,Main!$I$2:$I1000, "="&$B7, Main!$J$2:$J1000, "="&$A7, Main!$C$2:$C1000, "="&I$1) -> -3009.4 | J7: =SUMIFS(Main!$E$2:$E1000,Main!$I$2:$I1000, "="&$B7, Main!$J$2:$J1000, "="&$A7, Main!$C$2:$C1000, "="&J$1) -> -67000 | K7: =SUMIFS(Main!$E$2:$E1000,Main!$I$2:$I1000, "="&$B7, Main!$J$2:$J1000, "="&$A7, Main!$C$2:$C1000, "="&K$1) -> -8317 | ... U7: =SUMIFS(Main!$E$2:$E1000,Main!$I$2:$I1000, "="&$B7, Main!$J$2:$J1000, "="&$A7, Main!$C$2:$C1000, "="&U$1) -> 0 | V7: =Y6 -> 98667.78 | W7: =SUMIF($B7:$U7, "<0") -> -94303.71 | X7: =SUMIF($B7:$U7, ">0") -> 10728 | Y7: =V7+W7+X7 -> 15092.07
A8: =IFERROR(__xludf.DUMMYFUNCTION("SPLIT(C8, "" - "")"),2025.0) -> 2025 | B8: =IFERROR(__xludf.DUMMYFUNCTION("""COMPUTED_VALUE"""),2.0) -> 2 | C8: 2025 - 2 | D8: =SUMIFS(Main!$E$2:$E1000,Main!$I$2:$I1000, "="&$B8, Main!$J$2:$J1000, "="&$A8, Main!$C$2:$C1000, "="&D$1) -> -300 | E8: =SUMIFS(Main!$E$2:$E1000,Main!$I$2:$I1000, "="&$B8, Main!$J$2:$J1000, "="&$A8, Main!$C$2:$C1000, "="&E$1) -> -466 | F8: =SUMIFS(Main!$E$2:$E1000,Main!$I$2:$I1000, "="&$B8, Main!$J$2:$J1000, "="&$A8, Main!$C$2:$C1000, "="&F$1) -> 0 | G8: =SUMIFS(Main!$E$2:$E1000,Main!$I$2:$I1000, "="&$B8, Main!$J$2:$J1000, "="&$A8, Main!$C$2:$C1000, "="&G$1) -> -12456.2 | H8: =SUMIFS(Main!$E$2:$E1000,Main!$I$2:$I1000, "="&$B8, Main!$J$2:$J1000, "="&$A8, Main!$C$2:$C1000, "="&H$1) -> 0 | I8: =SUMIFS(Main!$E$2:$E1000,Main!$I$2:$I1000, "="&$B8, Main!$J$2:$J1000, "="&$A8, Main!$C$2:$C1000, "="&I$1) -> 0 | J8: =SUMIFS(Main!$E$2:$E1000,Main!$I$2:$I1000, "="&$B8, Main!$J$2:$J1000, "="&$A8, Main!$C$2:$C1000, "="&J$1) -> -15000 | K8: =SUMIFS(Main!$E$2:$E1000,Main!$I$2:$I1000, "="&$B8, Main!$J$2:$J1000, "="&$A8, Main!$C$2:$C1000, "="&K$1) -> -1709.78 | ... U8: =SUMIFS(Main!$E$2:$E1000,Main!$I$2:$I1000, "="&$B8, Main!$J$2:$J1000, "="&$A8, Main!$C$2:$C1000, "="&U$1) -> 0 | V8: =Y7 -> 15092.07 | W8: =SUMIF($B8:$U8, "<0") -> -40984.52 | X8: =SUMIF($B8:$U8, ">0") -> 159578 | Y8: =V8+W8+X8 -> 133685.55
A9: =IFERROR(__xludf.DUMMYFUNCTION("SPLIT(C9, "" - "")"),2025.0) -> 2025 | B9: =IFERROR(__xludf.DUMMYFUNCTION("""COMPUTED_VALUE"""),3.0) -> 3 | C9: 2025 - 3 | D9: =SUMIFS(Main!$E$2:$E1000,Main!$I$2:$I1000, "="&$B9, Main!$J$2:$J1000, "="&$A9, Main!$C$2:$C1000, "="&D$1) -> 0 | E9: =SUMIFS(Main!$E$2:$E1000,Main!$I$2:$I1000, "="&$B9, Main!$J$2:$J1000, "="&$A9, Main!$C$2:$C1000, "="&E$1) -> -3362.32 | F9: =SUMIFS(Main!$E$2:$E1000,Main!$I$2:$I1000, "="&$B9, Main!$J$2:$J1000, "="&$A9, Main!$C$2:$C1000, "="&F$1) -> 0 | G9: =SUMIFS(Main!$E$2:$E1000,Main!$I$2:$I1000, "="&$B9, Main!$J$2:$J1000, "="&$A9, Main!$C$2:$C1000, "="&G$1) -> -5668.82 | H9: =SUMIFS(Main!$E$2:$E1000,Main!$I$2:$I1000, "="&$B9, Main!$J$2:$J1000, "="&$A9, Main!$C$2:$C1000, "="&H$1) -> -5158 | I9: =SUMIFS(Main!$E$2:$E1000,Main!$I$2:$I1000, "="&$B9, Main!$J$2:$J1000, "="&$A9, Main!$C$2:$C1000, "="&I$1) -> -116.82 | J9: =SUMIFS(Main!$E$2:$E1000,Main!$I$2:$I1000, "="&$B9, Main!$J$2:$J1000, "="&$A9, Main!$C$2:$C1000, "="&J$1) -> -88000 | K9: =SUMIFS(Main!$E$2:$E1000,Main!$I$2:$I1000, "="&$B9, Main!$J$2:$J1000, "="&$A9, Main!$C$2:$C1000, "="&K$1) -> -7270 | ... U9: =SUMIFS(Main!$E$2:$E1000,Main!$I$2:$I1000, "="&$B9, Main!$J$2:$J1000, "="&$A9, Main!$C$2:$C1000, "="&U$1) -> 0 | V9: =Y8 -> 133685.55 | W9: =SUMIF($B9:$U9, "<0") -> -140554.92 | X9: =SUMIF($B9:$U9, ">0") -> 53963 | Y9: =V9+W9+X9 -> 47093.63
A10: =IFERROR(__xludf.DUMMYFUNCTION("SPLIT(C10, "" - "")"),2025.0) -> 2025 | B10: =IFERROR(__xludf.DUMMYFUNCTION("""COMPUTED_VALUE"""),4.0) -> 4 | C10: 2025 - 4 | D10: =SUMIFS(Main!$E$2:$E1000,Main!$I$2:$I1000, "="&$B10, Main!$J$2:$J1000, "="&$A10, Main!$C$2:$C1000, "="&D$1) -> 0 | E10: =SUMIFS(Main!$E$2:$E1000,Main!$I$2:$I1000, "="&$B10, Main!$J$2:$J1000, "="&$A10, Main!$C$2:$C1000, "="&E$1) -> -1671.35 | F10: =SUMIFS(Main!$E$2:$E1000,Main!$I$2:$I1000, "="&$B10, Main!$J$2:$J1000, "="&$A10, Main!$C$2:$C1000, "="&F$1) -> 0 | G10: =SUMIFS(Main!$E$2:$E1000,Main!$I$2:$I1000, "="&$B10, Main!$J$2:$J1000, "="&$A10, Main!$C$2:$C1000, "="&G$1) -> -8543.46 | H10: =SUMIFS(Main!$E$2:$E1000,Main!$I$2:$I1000, "="&$B10, Main!$J$2:$J1000, "="&$A10, Main!$C$2:$C1000, "="&H$1) -> 0 | I10: =SUMIFS(Main!$E$2:$E1000,Main!$I$2:$I1000, "="&$B10, Main!$J$2:$J1000, "="&$A10, Main!$C$2:$C1000, "="&I$1) -> -1036.26 | J10: =SUMIFS(Main!$E$2:$E1000,Main!$I$2:$I1000, "="&$B10, Main!$J$2:$J1000, "="&$A10, Main!$C$2:$C1000, "="&J$1) -> 20000 | K10: =SUMIFS(Main!$E$2:$E1000,Main!$I$2:$I1000, "="&$B10, Main!$J$2:$J1000, "="&$A10, Main!$C$2:$C1000, "="&K$1) -> -38745.53 | ... U10: =SUMIFS(Main!$E$2:$E1000,Main!$I$2:$I1000, "="&$B10, Main!$J$2:$J1000, "="&$A10, Main!$C$2:$C1000, "="&U$1) -> 0 | V10: =Y9 -> 47093.63 | W10: =SUMIF($B10:$U10, "<0") -> -127050.37 | X10: =SUMIF($B10:$U10, ">0") -> 99537 | Y10: =V10+W10+X10 -> 19580.26
A11: =IFERROR(__xludf.DUMMYFUNCTION("SPLIT(C11, "" - "")"),2025.0) -> 2025 | B11: =IFERROR(__xludf.DUMMYFUNCTION("""COMPUTED_VALUE"""),5.0) -> 5 | C11: 2025 - 5 | D11: =SUMIFS(Main!$E$2:$E1000,Main!$I$2:$I1000, "="&$B11, Main!$J$2:$J1000, "="&$A11, Main!$C$2:$C1000, "="&D$1) -> 0 | E11: =SUMIFS(Main!$E$2:$E1000,Main!$I$2:$I1000, "="&$B11, Main!$J$2:$J1000, "="&$A11, Main!$C$2:$C1000, "="&E$1) -> -12603.29 | F11: =SUMIFS(Main!$E$2:$E1000,Main!$I$2:$I1000, "="&$B11, Main!$J$2:$J1000, "="&$A11, Main!$C$2:$C1000, "="&F$1) -> 0 | G11: =SUMIFS(Main!$E$2:$E1000,Main!$I$2:$I1000, "="&$B11, Main!$J$2:$J1000, "="&$A11, Main!$C$2:$C1000, "="&G$1) -> -3579.43 | H11: =SUMIFS(Main!$E$2:$E1000,Main!$I$2:$I1000, "="&$B11, Main!$J$2:$J1000, "="&$A11, Main!$C$2:$C1000, "="&H$1) -> 0 | I11: =SUMIFS(Main!$E$2:$E1000,Main!$I$2:$I1000, "="&$B11, Main!$J$2:$J1000, "="&$A11, Main!$C$2:$C1000, "="&I$1) -> -2974.88 | J11: =SUMIFS(Main!$E$2:$E1000,Main!$I$2:$I1000, "="&$B11, Main!$J$2:$J1000, "="&$A11, Main!$C$2:$C1000, "="&J$1) -> -2990 | K11: =SUMIFS(Main!$E$2:$E1000,Main!$I$2:$I1000, "="&$B11, Main!$J$2:$J1000, "="&$A11, Main!$C$2:$C1000, "="&K$1) -> -43453 | ... U11: =SUMIFS(Main!$E$2:$E1000,Main!$I$2:$I1000, "="&$B11, Main!$J$2:$J1000, "="&$A11, Main!$C$2:$C1000, "="&U$1) -> 0 | V11: =Y10 -> 19580.26 | W11: =SUMIF($B11:$U11, "<0") -> -103740.29 | X11: =SUMIF($B11:$U11, ">0") -> 84373 | Y11: =V11+W11+X11 -> 212.97
A12: =IFERROR(__xludf.DUMMYFUNCTION("SPLIT(C12, "" - "")"),2025.0) -> 2025 | B12: =IFERROR(__xludf.DUMMYFUNCTION("""COMPUTED_VALUE"""),6.0) -> 6 | C12: 2025 - 6 | D12: =SUMIFS(Main!$E$2:$E1000,Main!$I$2:$I1000, "="&$B12, Main!$J$2:$J1000, "="&$A12, Main!$C$2:$C1000, "="&D$1) -> -300 | E12: =SUMIFS(Main!$E$2:$E1000,Main!$I$2:$I1000, "="&$B12, Main!$J$2:$J1000, "="&$A12, Main!$C$2:$C1000, "="&E$1) -> -230.23 | F12: =SUMIFS(Main!$E$2:$E1000,Main!$I$2:$I1000, "="&$B12, Main!$J$2:$J1000, "="&$A12, Main!$C$2:$C1000, "="&F$1) -> 0 | G12: =SUMIFS(Main!$E$2:$E1000,Main!$I$2:$I1000, "="&$B12, Main!$J$2:$J1000, "="&$A12, Main!$C$2:$C1000, "="&G$1) -> -23120 | H12: =SUMIFS(Main!$E$2:$E1000,Main!$I$2:$I1000, "="&$B12, Main!$J$2:$J1000, "="&$A12, Main!$C$2:$C1000, "="&H$1) -> -7120 | I12: =SUMIFS(Main!$E$2:$E1000,Main!$I$2:$I1000, "="&$B12, Main!$J$2:$J1000, "="&$A12, Main!$C$2:$C1000, "="&I$1) -> -1780.44 | J12: =SUMIFS(Main!$E$2:$E1000,Main!$I$2:$I1000, "="&$B12, Main!$J$2:$J1000, "="&$A12, Main!$C$2:$C1000, "="&J$1) -> -30000 | K12: =SUMIFS(Main!$E$2:$E1000,Main!$I$2:$I1000, "="&$B12, Main!$J$2:$J1000, "="&$A12, Main!$C$2:$C1000, "="&K$1) -> -11825.88 | ... U12: =SUMIFS(Main!$E$2:$E1000,Main!$I$2:$I1000, "="&$B12, Main!$J$2:$J1000, "="&$A12, Main!$C$2:$C1000, "="&U$1) -> 0 | V12: =Y11 -> 212.97 | W12: =SUMIF($B12:$U12, "<0") -> -116492.1 | X12: =SUMIF($B12:$U12, ">0") -> 133550 | Y12: =V12+W12+X12 -> 17270.87
A13: =IFERROR(__xludf.DUMMYFUNCTION("SPLIT(C13, "" - "")"),2025.0) -> 2025 | B13: =IFERROR(__xludf.DUMMYFUNCTION("""COMPUTED_VALUE"""),7.0) -> 7 | C13: 2025 - 7 | D13: =SUMIFS(Main!$E$2:$E1000,Main!$I$2:$I1000, "="&$B13, Main!$J$2:$J1000, "="&$A13, Main!$C$2:$C1000, "="&D$1) -> 0 | E13: =SUMIFS(Main!$E$2:$E1000,Main!$I$2:$I1000, "="&$B13, Main!$J$2:$J1000, "="&$A13, Main!$C$2:$C1000, "="&E$1) -> -8972 | F13: =SUMIFS(Main!$E$2:$E1000,Main!$I$2:$I1000, "="&$B13, Main!$J$2:$J1000, "="&$A13, Main!$C$2:$C1000, "="&F$1) -> 0 | G13: =SUMIFS(Main!$E$2:$E1000,Main!$I$2:$I1000, "="&$B13, Main!$J$2:$J1000, "="&$A13, Main!$C$2:$C1000, "="&G$1) -> -3638.66 | H13: =SUMIFS(Main!$E$2:$E1000,Main!$I$2:$I1000, "="&$B13, Main!$J$2:$J1000, "="&$A13, Main!$C$2:$C1000, "="&H$1) -> -7000 | I13: =SUMIFS(Main!$E$2:$E1000,Main!$I$2:$I1000, "="&$B13, Main!$J$2:$J1000, "="&$A13, Main!$C$2:$C1000, "="&I$1) -> -14484.82 | J13: =SUMIFS(Main!$E$2:$E1000,Main!$I$2:$I1000, "="&$B13, Main!$J$2:$J1000, "="&$A13, Main!$C$2:$C1000, "="&J$1) -> 0 | K13: =SUMIFS(Main!$E$2:$E1000,Main!$I$2:$I1000, "="&$B13, Main!$J$2:$J1000, "="&$A13, Main!$C$2:$C1000, "="&K$1) -> -9908 | ... U13: =SUMIFS(Main!$E$2:$E1000,Main!$I$2:$I1000, "="&$B13, Main!$J$2:$J1000, "="&$A13, Main!$C$2:$C1000, "="&U$1) -> 0 | V13: =Y12 -> 17270.87 | W13: =SUMIF($B13:$U13, "<0") -> -90721.9 | X13: =SUMIF($B13:$U13, ">0") -> 96123 | Y13: =V13+W13+X13 -> 22671.97
A14: =IFERROR(__xludf.DUMMYFUNCTION("SPLIT(C14, "" - "")"),2025.0) -> 2025 | B14: =IFERROR(__xludf.DUMMYFUNCTION("""COMPUTED_VALUE"""),8.0) -> 8 | C14: 2025 - 8 | D14: =SUMIFS(Main!$E$2:$E1000,Main!$I$2:$I1000, "="&$B14, Main!$J$2:$J1000, "="&$A14, Main!$C$2:$C1000, "="&D$1) -> 0 | E14: =SUMIFS(Main!$E$2:$E1000,Main!$I$2:$I1000, "="&$B14, Main!$J$2:$J1000, "="&$A14, Main!$C$2:$C1000, "="&E$1) -> -2368.94 | F14: =SUMIFS(Main!$E$2:$E1000,Main!$I$2:$I1000, "="&$B14, Main!$J$2:$J1000, "="&$A14, Main!$C$2:$C1000, "="&F$1) -> 0 | G14: =SUMIFS(Main!$E$2:$E1000,Main!$I$2:$I1000, "="&$B14, Main!$J$2:$J1000, "="&$A14, Main!$C$2:$C1000, "="&G$1) -> -2165.29 | H14: =SUMIFS(Main!$E$2:$E1000,Main!$I$2:$I1000, "="&$B14, Main!$J$2:$J1000, "="&$A14, Main!$C$2:$C1000, "="&H$1) -> -17000 | I14: =SUMIFS(Main!$E$2:$E1000,Main!$I$2:$I1000, "="&$B14, Main!$J$2:$J1000, "="&$A14, Main!$C$2:$C1000, "="&I$1) -> -1947 | J14: =SUMIFS(Main!$E$2:$E1000,Main!$I$2:$I1000, "="&$B14, Main!$J$2:$J1000, "="&$A14, Main!$C$2:$C1000, "="&J$1) -> 0 | K14: =SUMIFS(Main!$E$2:$E1000,Main!$I$2:$I1000, "="&$B14, Main!$J$2:$J1000, "="&$A14, Main!$C$2:$C1000, "="&K$1) -> -17123 | ... U14: =SUMIFS(Main!$E$2:$E1000,Main!$I$2:$I1000, "="&$B14, Main!$J$2:$J1000, "="&$A14, Main!$C$2:$C1000, "="&U$1) -> 7 | V14: =Y13 -> 22671.97 | W14: =SUMIF($B14:$U14, "<0") -> -81634.16 | X14: =SUMIF($B14:$U14, ">0") -> 116168 | Y14: =V14+W14+X14 -> 57205.81
A15: =IFERROR(__xludf.DUMMYFUNCTION("SPLIT(C15, "" - "")"),2025.0) -> 2025 | B15: =IFERROR(__xludf.DUMMYFUNCTION("""COMPUTED_VALUE"""),9.0) -> 9 | C15: 2025 - 9 | D15: =SUMIFS(Main!$E$2:$E1000,Main!$I$2:$I1000, "="&$B15, Main!$J$2:$J1000, "="&$A15, Main!$C$2:$C1000, "="&D$1) -> -1300 | E15: =SUMIFS(Main!$E$2:$E1000,Main!$I$2:$I1000, "="&$B15, Main!$J$2:$J1000, "="&$A15, Main!$C$2:$C1000, "="&E$1) -> -12877 | F15: =SUMIFS(Main!$E$2:$E1000,Main!$I$2:$I1000, "="&$B15, Main!$J$2:$J1000, "="&$A15, Main!$C$2:$C1000, "="&F$1) -> 0 | G15: =SUMIFS(Main!$E$2:$E1000,Main!$I$2:$I1000, "="&$B15, Main!$J$2:$J1000, "="&$A15, Main!$C$2:$C1000, "="&G$1) -> -1729.86 | H15: =SUMIFS(Main!$E$2:$E1000,Main!$I$2:$I1000, "="&$B15, Main!$J$2:$J1000, "="&$A15, Main!$C$2:$C1000, "="&H$1) -> -1000 | I15: =SUMIFS(Main!$E$2:$E1000,Main!$I$2:$I1000, "="&$B15, Main!$J$2:$J1000, "="&$A15, Main!$C$2:$C1000, "="&I$1) -> -11118.22 | J15: =SUMIFS(Main!$E$2:$E1000,Main!$I$2:$I1000, "="&$B15, Main!$J$2:$J1000, "="&$A15, Main!$C$2:$C1000, "="&J$1) -> -25000 | K15: =SUMIFS(Main!$E$2:$E1000,Main!$I$2:$I1000, "="&$B15, Main!$J$2:$J1000, "="&$A15, Main!$C$2:$C1000, "="&K$1) -> -10452.14 | ... U15: =SUMIFS(Main!$E$2:$E1000,Main!$I$2:$I1000, "="&$B15, Main!$J$2:$J1000, "="&$A15, Main!$C$2:$C1000, "="&U$1) -> 0 | V15: =Y14 -> 57205.81 | W15: =SUMIF($B15:$U15, "<0") -> -118707.62 | X15: =SUMIF($B15:$U15, ">0") -> 123823.15 | Y15: =V15+W15+X15 -> 62321.34

Sheet Charts

Sheet Billings
A1: Platform | B1: Status | C1: Type | D1: Cost | E1: Per Month | F1: Per Year
A2: Netflix | B2: Active | C2: Monthly | D2: 645 | E2: =IF(EQ(C2, "Monthly"), D2, D2 / 12) -> 645 | F2: =IF(EQ(C2, "Monthly"), D2 * 12, D2) -> 7740
A3: Google One | B3: Active | C3: Yearly | D3: 6500 | E3: =IF(EQ(C3, "Monthly"), D3, D3 / 12) -> 541.66667 | F3: =IF(EQ(C3, "Monthly"), D3 * 12, D3) -> 6500
A4: YouTube Premium | B4: Active | C4: Monthly | D4: 299 | E4: =IF(EQ(C4, "Monthly"), D4, D4 / 12) -> 299 | F4: =IF(EQ(C4, "Monthly"), D4 * 12, D4) -> 3588
A5: Amazon Prime | B5: Active | C5: Yearly | D5: 799 | E5: =IF(EQ(C5, "Monthly"), D5, D5 / 12) -> 66.583333 | F5: =IF(EQ(C5, "Monthly"), D5 * 12, D5) -> 799
A6: Souled Store | B6: Inactive | C6: Monthly | D6: 66.33 | E6: =IF(EQ(C6, "Monthly"), D6, D6 / 12) -> 66.33 | F6: =IF(EQ(C6, "Monthly"), D6 * 12, D6) -> 795.96
A7: Airtel Postpaid | B7: Active | C7: Monthly | D7: 529.82 | E7: =IF(EQ(C7, "Monthly"), D7, D7 / 12) -> 529.82 | F7: =IF(EQ(C7, "Monthly"), D7 * 12, D7) -> 6357.84
A8: Aitel Wifi | B8: Active | C8: Monthly | D8: 1295.64 | E8: =IF(EQ(C8, "Monthly"), D8, D8 / 12) -> 1295.64 | F8: =IF(EQ(C8, "Monthly"), D8 * 12, D8) -> 15547.68
A9: Airtel DTH | B9: Active | C9: Monthly | D9: 310 | E9: =IF(EQ(C9, "Monthly"), D9, D9 / 12) -> 310 | F9: =IF(EQ(C9, "Monthly"), D9 * 12, D9) -> 3720
A10: Rent | B10: Active | C10: Monthly | D10: 20000 | E10: =IF(EQ(C10, "Monthly"), D10, D10 / 12) -> 20000 | F10: =IF(EQ(C10, "Monthly"), D10 * 12, D10) -> 240000
B11: Active
B12: Active
B13: Active
B14: Active
A16: Totals | C16: Monthly | D16: =SUMIF(C2:C14, "Monthly", D2:D14) -> 23145.79 | E16: =IF(EQ(C16, "Monthly"), D16, D16 / 12) -> 23145.79 | F16: =IF(EQ(C16, "Monthly"), D16 * 12, D16) -> 277749.48
C17: Yearly | D17: =SUMIF(C2:C14, "Yearly", D2:D14) -> 7299 | E17: =IF(EQ(C17, "Monthly"), D17, D17 / 12) -> 608.25 | F17: =IF(EQ(C17, "Monthly"), D17 * 12, D17) -> 7299

Sheet Pivots
